whisper_cli/__init__.py
whisper_cli/env.py
whisper_cli/main.py
whisper_cli/utils.py
whisper_cli-0.0.5.dist-info/LICENSE
whisper_cli-0.0.5.dist-info/WHEEL
whisper_cli-0.0.5.dist-info/entry_points.txt
whisper_cli-0.0.5.dist-info/METADATA
whisper_cli-0.0.5.dist-info/RECORD
