Metadata-Version: 2.1
Name: whisper-cli
Version: 0.0.5
Summary: A command-line interface for transcribing and translating audio using OpenAI's Whisper API
License: MIT
Author: Vatsal
Author-email: vatsalaggarwal@gmail.com
Requires-Python: >=3.10,<4.0
Classifier: License :: OSI Approved :: MIT License
Classifier: Programming Language :: Python :: 3
Classifier: Programming Language :: Python :: 3.10
Classifier: Programming Language :: Python :: 3.11
Requires-Dist: openai (>=0.27.0,<0.28.0)
Requires-Dist: toml (>=0.10.2,<0.11.0)
Requires-Dist: typer[all] (>=0.7.0,<0.8.0)
